update_conf_py_do_not_use/__init__.py
update_conf_py_do_not_use/main.py
update_conf_py_do_not_use-1.1.0.dev7.data/data/share/update-conf-py-do-not-use/update-conf-py-do-not-use.conf
update_conf_py_do_not_use-1.1.0.dev7.dist-info/LICENSE
update_conf_py_do_not_use-1.1.0.dev7.dist-info/METADATA
update_conf_py_do_not_use-1.1.0.dev7.dist-info/WHEEL
update_conf_py_do_not_use-1.1.0.dev7.dist-info/entry_points.txt
update_conf_py_do_not_use-1.1.0.dev7.dist-info/top_level.txt
update_conf_py_do_not_use-1.1.0.dev7.dist-info/RECORD
