Metadata-Version: 2.1
Name: update-conf-py-do-not-use
Version: 1.1.0.dev7
Summary: Generate config files from 'conf.d' like directories
Home-page: https://us-east-1.console.aws.amazon.com/codesuite/codecommit/repositories/update-conf-py-DO-NOT-USE/
Author: Rarylson Freitas
Author-email: rarylson@gmail.com
License: Revised BSD
Keywords: system unix config split merge snippets sysadmin
Classifier: Development Status :: 1 - Planning
Classifier: Environment :: Console
Classifier: Intended Audience :: System Administrators
Classifier: License :: OSI Approved
Classifier: Natural Language :: English
Classifier: Operating System :: MacOS :: MacOS X
Classifier: Operating System :: POSIX
Classifier: Programming Language :: Python :: 3.7
Classifier: Programming Language :: Python :: 3.8
Classifier: Programming Language :: Python :: 3.9
Classifier: Programming Language :: Python :: 3.10
Classifier: Topic :: System :: Systems Administration
Classifier: Topic :: Utilities
Requires-Python: >=3.7
License-File: LICENSE
